{
  "timestamp": "2026-05-02T09:48:04.850125+00:00",
  "snapshot": {
    "events_total": 12799,
    "counters": {
      "api_requests_total": 6932,
      "api_requests_GET_/health": 99,
      "api_status_2xx": 6931,
      "api_requests_POST_/predict": 5868,
      "predictions_total": 5867,
      "predictions_risk_low": 4267,
      "predictions_risk_medium": 419,
      "predictions_risk_high": 1181,
      "api_requests_GET_/predictions": 499,
      "api_requests_GET_/monitor": 466,
      "prediction_validation_errors": 1,
      "api_status_4xx": 1
    },
    "latency": {
      "count": 5000,
      "avg_ms": 821.7732036797563,
      "p95_ms": 370.7680000225082
    },
    "drift_stub": {
      "status": "alert",
      "baseline_mean": 0.5,
      "current_mean": 0.249215661974437,
      "distance": 0.250784338025563,
      "samples": 1000,
      "threshold": 0.1
    }
  },
  "summary": {
    "total_events": 12799,
    "event_types": {
      "latency": 6932,
      "prediction": 5867
    },
    "modules": {
      "api": 12799
    },
    "duration_seconds": 14201.063491
  }
}