{
  "timestamp": "2026-05-02T08:02:30.653046+00:00",
  "snapshot": {
    "events_total": 7812,
    "counters": {
      "api_requests_total": 4437,
      "api_requests_GET_/health": 97,
      "api_status_2xx": 4436,
      "api_requests_POST_/predict": 3376,
      "predictions_total": 3375,
      "predictions_risk_low": 2439,
      "predictions_risk_medium": 249,
      "predictions_risk_high": 687,
      "api_requests_GET_/predictions": 498,
      "api_requests_GET_/monitor": 466,
      "prediction_validation_errors": 1,
      "api_status_4xx": 1
    },
    "latency": {
      "count": 4437,
      "avg_ms": 110.22241451389571,
      "p95_ms": 410.2356999646872
    },
    "drift_stub": {
      "status": "alert",
      "baseline_mean": 0.5,
      "current_mean": 0.2659892048448968,
      "distance": 0.2340107951551032,
      "samples": 1000,
      "threshold": 0.1
    }
  },
  "summary": {
    "total_events": 7812,
    "event_types": {
      "latency": 4437,
      "prediction": 3375
    },
    "modules": {
      "api": 7812
    },
    "duration_seconds": 7871.520422
  }
}